PyFEBOL/PyFEBOL.py
PyFEBOL/__init__.py
PyFEBOL/cost.py
PyFEBOL/drone.py
PyFEBOL/filter.py
PyFEBOL/policy.py
PyFEBOL/searchdomain.py
PyFEBOL/sensor.py
PyFEBOL/test.py
PyFEBOL/util.py
PyFEBOL-0.1.3.dist-info/METADATA
PyFEBOL-0.1.3.dist-info/RECORD
PyFEBOL-0.1.3.dist-info/WHEEL
PyFEBOL-0.1.3.dist-info/top_level.txt
