Metadata-Version: 2.1
Name: PyFEBOL
Version: 0.1.3
Summary: Python Filter Exploration for Bearing Only Localization
Home-page: https://github.com/cdrckrgt/PyFEBOL
Author: Cedrick Argueta
Author-email: cedrick@cs.stanford.edu
License: MIT
Platform: UNKNOWN
